cateye/__init__.py
cateye/cateye.py
cateye-0.4.4.dist-info/LICENSE
cateye-0.4.4.dist-info/METADATA
cateye-0.4.4.dist-info/WHEEL
cateye-0.4.4.dist-info/entry_points.txt
cateye-0.4.4.dist-info/top_level.txt
cateye-0.4.4.dist-info/RECORD
