Metadata-Version: 2.1
Name: cateye
Version: 0.4.4
Summary: A hint-enabled search engine framework for biomedical classification systems
Home-page: https://github.com/jeroyang/cateye
Author: Chia-Jung, Yang
Author-email: jeroyang@gmail.com
License: MIT
Keywords: cateye
Platform: UNKNOWN
Classifier: Development Status :: 4 - Beta
Classifier: Intended Audience :: Developers
Classifier: License :: OSI Approved :: MIT License
Classifier: Natural Language :: English
Classifier: Programming Language :: Python :: 3
Classifier: Programming Language :: Python :: 3.3
Classifier: Programming Language :: Python :: 3.4
Classifier: Programming Language :: Python :: 3.5
Classifier: Programming Language :: Python :: 3.6
Requires-Dist: Flask (==1.0.2)
Requires-Dist: shove (==0.6.6)
